{
  "appPageId" : "5bac5498-8789-4520-a16d-0a90bca958b6",
  "componentName" : "siteforce:sldsOneColLayout",
  "dataProviders" : [ ],
  "id" : "115b86db-ca6f-452c-900b-e5ea54d0de6a",
  "label" : "Action Plan Template Related List",
  "regions" : [ {
    "id" : "da8f2204-6576-4aab-8770-ebe31b923d6f",
    "regionName" : "header",
    "type" : "region"
  }, {
    "components" : [ {
      "componentAttributes" : {
        "customTitle" : "",
        "parentRecordId" : "{!recordId}",
        "relatedListName" : "{!relationshipApiName}",
        "showBreadCrumbs" : true,
        "showCustomTitle" : false,
        "showManualRefreshButton" : true,
        "showRowNumbers" : true
      },
      "componentName" : "forceCommunity:relatedList",
      "id" : "6b4c1317-4416-411f-add9-8d3575f3b826",
      "renderPriority" : "NEUTRAL",
      "renditionMap" : { },
      "type" : "component"
    } ],
    "id" : "0a1e12ad-681a-48ac-a2b2-ed69ef6270ae",
    "regionName" : "content",
    "type" : "region"
  }, {
    "id" : "38eb88f3-dd12-4e70-b14a-41c9e5dd8909",
    "regionName" : "footer",
    "type" : "region"
  } ],
  "themeLayoutType" : "Inner",
  "type" : "view",
  "viewType" : "relatedlist-0PR"
}