{
  "appPageId" : "a1c9d74d-4159-4bec-bd89-3c3a9de0d6cf",
  "componentName" : "siteforce:dynamicLayout",
  "id" : "46aa8de0-2467-4ce6-a3d6-e84a0f385fbe",
  "label" : "Order Summary Detail",
  "regions" : [ {
    "components" : [ {
      "componentAttributes" : {
        "background" : "background: rgba(0,0,0,0)",
        "backgroundOverlay" : "rgba(0,0,0,0.5)",
        "contentAreaWidth" : 100,
        "sectionConfig" : {
          "UUID" : "6a919de3-16c3-493a-bf65-c85ac50c5c46",
          "columns" : [ {
            "UUID" : "f7749331-322f-42a4-ba5e-9b69a62c4479",
            "columnKey" : "col1",
            "columnName" : "column 1",
            "columnWidth" : "12",
            "seedComponents" : [ {
              "attributes" : {
                "recordId" : "{!recordId}",
                "sfdc:identifier" : "b2b_buyer_builder_orderSummaryDetailsHeader"
              },
              "fqn" : "b2b_buyer_builder:orderSummaryDetailsHeader"
            } ]
          } ]
        },
        "sectionHeight" : 32
      },
      "componentName" : "forceCommunity:section",
      "id" : "6a919de3-16c3-493a-bf65-c85ac50c5c46",
      "regions" : [ {
        "components" : [ {
          "componentAttributes" : {
            "showOrderNumber" : true,
            "startReOrderButtonBackgroundColor" : "",
            "startReOrderButtonBackgroundHoverColor" : "",
            "startReOrderButtonBorderColor" : "",
            "startReOrderButtonBorderRadius" : "0",
            "startReOrderButtonText" : "START REORDER",
            "startReOrderButtonTextColor" : "",
            "startReOrderButtonTextHoverColor" : "",
            "title" : "My Order"
          },
          "componentName" : "b2b_buyer_builder:orderSummaryDetailsHeader",
          "id" : "3683ceaf-fd7c-4571-a118-beabde092ff5",
          "renderPriority" : "NEUTRAL",
          "renditionMap" : { },
          "type" : "component"
        } ],
        "id" : "f7749331-322f-42a4-ba5e-9b69a62c4479",
        "regionLabel" : "column 1",
        "regionName" : "col1",
        "renditionMap" : { },
        "type" : "region"
      } ],
      "renderPriority" : "NEUTRAL",
      "renditionMap" : { },
      "type" : "component"
    }, {
      "componentAttributes" : {
        "background" : "background: rgba(0,0,0,0)",
        "backgroundOverlay" : "rgba(0,0,0,0.5)",
        "contentAreaWidth" : 100,
        "sectionConfig" : {
          "UUID" : "8ea3852a-78bf-4e54-b047-0aa6f0982bf0",
          "columns" : [ {
            "UUID" : "5302c315-711e-4a3a-9894-59617af8c495",
            "columnKey" : "col1",
            "columnName" : "column 1",
            "columnWidth" : "4",
            "seedComponents" : [ {
              "attributes" : {
                "recordId" : "{!recordId}",
                "sfdc:identifier" : "b2b_buyer_builder_orderSummaryHighlights"
              },
              "fqn" : "b2b_buyer_builder:orderSummaryHighlights"
            }, {
              "attributes" : {
                "recordId" : "{!recordId}",
                "sfdc:identifier" : "b2b_buyer_builder_orderSummaryTotals"
              },
              "fqn" : "b2b_buyer_builder:orderSummaryTotals"
            }, {
              "attributes" : {
                "recordId" : "{!recordId}",
                "sfdc:identifier" : "b2b_buyer_builder_orderSummaryAppliedPromotions"
              },
              "fqn" : "b2b_buyer_builder:orderSummaryAppliedPromotions"
            } ]
          }, {
            "UUID" : "82fd21ec-8e53-454e-afc7-7b98bb06b2cd",
            "columnKey" : "col2",
            "columnName" : "column 2",
            "columnWidth" : "8",
            "seedComponents" : [ {
              "attributes" : {
                "recordId" : "{!recordId}",
                "sfdc:identifier" : "b2b_buyer_builder_orderItemSummaryContents"
              },
              "fqn" : "b2b_buyer_builder:orderItemSummaryContents"
            } ]
          } ]
        },
        "sectionHeight" : 32
      },
      "componentName" : "forceCommunity:section",
      "id" : "8ea3852a-78bf-4e54-b047-0aa6f0982bf0",
      "regions" : [ {
        "components" : [ {
          "componentAttributes" : {
            "highlightsCardBackgroundColor" : "#FFFFFF",
            "highlightsCardBorderColor" : "",
            "highlightsCardBorderRadius" : "0",
            "highlightsCardTextColor" : "",
            "highlightsTitle" : "Details",
            "orderSummaryHighlightsFieldMapping" : ""
          },
          "componentName" : "b2b_buyer_builder:orderSummaryHighlights",
          "id" : "f44b5bd8-10a6-4e19-b59f-3b47594940e1",
          "renderPriority" : "NEUTRAL",
          "renditionMap" : { },
          "type" : "component"
        }, {
          "componentAttributes" : {
            "grossTaxOrdersFieldMapping" : "",
            "netTaxOrdersFieldMapping" : "",
            "showHorizontalLineAboveLastField" : true,
            "showLastFieldAsBold" : true,
            "totalsCardBackgroundColor" : "#FFFFFF",
            "totalsCardBorderColor" : "",
            "totalsCardBorderRadius" : "0",
            "totalsCardTextColor" : "",
            "totalsCardTitle" : "Totals"
          },
          "componentName" : "b2b_buyer_builder:orderSummaryTotals",
          "id" : "25597daa-3c49-4631-ba3d-fd56d4ec9089",
          "renderPriority" : "NEUTRAL",
          "renditionMap" : { },
          "type" : "component"
        }, {
          "componentAttributes" : {
            "appliedPromAmountTextColor" : "",
            "appliedPromCardBackgroundColor" : "#FFFFFF",
            "appliedPromCardBorderColor" : "",
            "appliedPromCardBorderRadius" : "0",
            "appliedPromCardTitle" : "Applied Promotions",
            "appliedPromTextColor" : ""
          },
          "componentName" : "b2b_buyer_builder:orderSummaryAppliedPromotions",
          "id" : "07f29aa0-c98a-4f2f-a19c-aa5522ba2521",
          "renderPriority" : "NEUTRAL",
          "renditionMap" : { },
          "type" : "component"
        } ],
        "id" : "5302c315-711e-4a3a-9894-59617af8c495",
        "regionLabel" : "column 1",
        "regionName" : "col1",
        "renditionMap" : { },
        "type" : "region"
      }, {
        "components" : [ {
          "componentAttributes" : {
            "adjustmentsAmountTextColor" : "#333333",
            "otherAdjustmentsLabel" : "Other Adjustments",
            "prefixToShippingGroup" : "Ship To",
            "productFieldMapping" : "",
            "productUnavailableMessage" : "(No More Available)",
            "shippingGroupFieldMapping" : "",
            "showProductImage" : true
          },
          "componentName" : "b2b_buyer_builder:orderItemSummaryContents",
          "id" : "221fcb2c-9e9a-4f44-bd45-faaf4df4108e",
          "renderPriority" : "NEUTRAL",
          "renditionMap" : { },
          "type" : "component"
        } ],
        "id" : "82fd21ec-8e53-454e-afc7-7b98bb06b2cd",
        "regionLabel" : "column 2",
        "regionName" : "col2",
        "renditionMap" : { },
        "type" : "region"
      } ],
      "renderPriority" : "NEUTRAL",
      "renditionMap" : { },
      "type" : "component"
    } ],
    "id" : "3868038d-b0b5-4ebe-b04d-0a60f1dc4533",
    "regionName" : "content",
    "type" : "region"
  }, {
    "components" : [ {
      "componentAttributes" : {
        "customHeadTags" : "",
        "description" : "",
        "title" : "{!Record._Object}: {!Record._Title}"
      },
      "componentName" : "forceCommunity:seoAssistant",
      "id" : "12f6f86d-444f-4027-b72e-1fb4deb1b75a",
      "renditionMap" : { },
      "type" : "component"
    } ],
    "id" : "6cd5d280-8abc-4a89-9557-5ca2ef0a572a",
    "regionName" : "sfdcHiddenRegion",
    "type" : "region"
  } ],
  "themeLayoutType" : "Inner",
  "type" : "view",
  "viewType" : "detail-1Os"
}