{
  "appPageId" : "a1c9d74d-4159-4bec-bd89-3c3a9de0d6cf",
  "componentName" : "siteforce:sldsOneColLayout",
  "id" : "7c0ac323-b59e-4f50-9946-da31902e441d",
  "label" : "Service Not Available",
  "regions" : [ {
    "components" : [ {
      "componentAttributes" : {
        "richTextValue" : "<div style='display: flex; align-items: center; flex-direction: column; margin: 60px 25px 40px 25px;'><div style='background: url(/sfsites/assets/Images/serviceNotAvailable/serviceNotAvailable.svg) center no-repeat; background-size: contain; height: 331px; width: 100%; max-width: 538px;'></div></div><div style='margin: 0 25px; text-align: center;'><h1><b style='font-size: 2em'>Looks like the site is temporarily unavailable</b></h1><br/><p><span style='font-size: 1.5em;'>Please try again in a bit.</span></p></div>"
      },
      "componentName" : "forceCommunity:htmlBlock",
      "id" : "6ed3557f-607c-4541-a177-9a569aeaad4d",
      "renderPriority" : "NEUTRAL",
      "renditionMap" : { },
      "type" : "component"
    } ],
    "id" : "3aedbeac-f68f-49c5-bf8f-4bcc24b1cef1",
    "regionName" : "content",
    "type" : "region"
  } ],
  "themeLayoutType" : "ServiceNotAvailable",
  "type" : "view",
  "viewType" : "service-not-available"
}