{
  "appPageId" : "9ed1ba93-e365-4552-8f42-0719b5d0c55e",
  "componentName" : "siteforce:sldsTwoCol84Layout",
  "id" : "62860aee-f5f0-46cb-a395-6673d33eb67b",
  "label" : "Home",
  "regions" : [ {
    "components" : [ {
      "componentAttributes" : {
        "richTextValue" : "<img class='sfdcCbImage' src='/sfsites/c/img/community/cpt/cpt-home-banner.png'             style='width:100%;'/>"
      },
      "componentName" : "forceCommunity:richTextInline",
      "id" : "5bf50ee5-7086-490d-90df-62280b7fc4fc",
      "renderPriority" : "NEUTRAL",
      "renditionMap" : { },
      "type" : "component"
    }, {
      "componentAttributes" : {
        "gatewayId" : "INSERT_GATEWAY",
        "pricebookId" : "INSERT_PRICEBOOK"
      },
      "componentName" : "c:sm_CommunityCheckout",
      "id" : "c55bb403-c011-4977-981f-4076bc9985d7",
      "renderPriority" : "NEUTRAL",
      "renditionMap" : { },
      "type" : "component"
    }, {
      "componentAttributes" : {
        "bannerBackgroundColor" : "",
        "bannerPosition" : "top",
        "bannerSizePercent" : 35,
        "borderRadius" : 20,
        "boxShadow" : true,
        "haveBanner" : false,
        "iconBackgroundColor" : "rgb(255,255,255)",
        "iconSize" : "medium",
        "noImageColor" : "rgb(212, 212, 212)",
        "overlay" : "rgba(0,0,0,0.01)",
        "templateType" : "default",
        "tileMenuEditor" : "Subscription_Management",
        "titleColor" : "",
        "titleFontSize" : "medium",
        "titleHorizontalAlign" : "center"
      },
      "componentName" : "community_navigation:tileMenu",
      "id" : "5e8d4b3f-0e49-4a1a-8047-b631d318f1d8",
      "renderPriority" : "NEUTRAL",
      "renditionMap" : { },
      "type" : "component"
    } ],
    "id" : "97f04f20-3fd5-4337-b587-e8bd4f777479",
    "regionName" : "header",
    "type" : "region"
  }, {
    "id" : "2c9f6c91-acb4-47d7-b530-809ee6e86df3",
    "regionName" : "content",
    "type" : "region"
  }, {
    "id" : "6adfa3c4-849a-408f-bb5d-bf7a14092e7f",
    "regionName" : "sidebar",
    "type" : "region"
  }, {
    "id" : "3535b18b-142f-4680-a34a-8873d4b88964",
    "regionName" : "footer",
    "type" : "region"
  }, {
    "components" : [ {
      "componentAttributes" : {
        "customHeadTags" : "",
        "description" : "",
        "title" : "Home"
      },
      "componentName" : "forceCommunity:seoAssistant",
      "id" : "118d69ef-13c7-409c-8518-149c4226ac05",
      "renditionMap" : { },
      "type" : "component"
    } ],
    "id" : "9100d502-eced-47ff-8d9f-eedb3b9a3d40",
    "regionName" : "sfdcHiddenRegion",
    "type" : "region"
  } ],
  "themeLayoutType" : "Inner",
  "type" : "view",
  "viewType" : "home"
}