{
    "records": [
        {
            "attributes": {
                "type": "PricebookEntry",
                "referenceId": "PricebookEntryRef1"
            },
            "IsActive": true,
            "UnitPrice": 1000,
            "UseStandardPrice": false,
            "Product2Id":"@Product2Ref1",
            "ProductSellingModelId": "@ProductSellingModelRef2",
            "Pricebook2Id": "STANDARD_PRICEBOOK_ID",
            "CurrencyISOCode": "USD"
        },
        {
            "attributes": {
                "type": "PricebookEntry",
                "referenceId": "PricebookEntryRef2"
            },
            "IsActive": true,
            "UnitPrice": 100,
            "UseStandardPrice": false,
            "Product2Id":"@Product2Ref2",
            "ProductSellingModelId": "@ProductSellingModelRef1",
            "Pricebook2Id": "STANDARD_PRICEBOOK_ID",
            "CurrencyISOCode": "USD"
        },
        {
            "attributes": {
                "type": "PricebookEntry",
                "referenceId": "PricebookEntryRef3"
            },
            "IsActive": true,
            "UnitPrice": 500,
            "UseStandardPrice": false,
            "Product2Id":"@Product2Ref3",
            "ProductSellingModelId": "@ProductSellingModelRef3",
            "Pricebook2Id": "STANDARD_PRICEBOOK_ID",
            "CurrencyISOCode": "USD"
        },
        {
            "attributes": {
                "type": "PricebookEntry",
                "referenceId": "PricebookEntryRef4"
            },
            "IsActive": true,
            "UnitPrice": 25,
            "UseStandardPrice": false,
            "Product2Id":"@Product2Ref4",
            "ProductSellingModelId": "@ProductSellingModelRef1",
            "Pricebook2Id": "STANDARD_PRICEBOOK_ID",
            "CurrencyISOCode": "USD"
        },
        {
            "attributes": {
                "type": "PricebookEntry",
                "referenceId": "PricebookEntryRef5"
            },
            "IsActive": true,
            "UnitPrice": 35,
            "UseStandardPrice": false,
            "Product2Id":"@Product2Ref4",
            "ProductSellingModelId": "@ProductSellingModelRef3",
            "Pricebook2Id": "STANDARD_PRICEBOOK_ID",
            "CurrencyISOCode": "USD"
        },
        {
            "attributes": {
                "type": "PricebookEntry",
                "referenceId": "PricebookEntryRef6"
            },
            "IsActive": true,
            "UnitPrice": 1000,
            "UseStandardPrice": false,
            "Product2Id":"@Product2Ref1",
            "ProductSellingModelId": "@ProductSellingModelRef2",
            "Pricebook2Id": "SM_PRICEBOOK_ID",
            "CurrencyISOCode": "USD"
        },
        {
            "attributes": {
                "type": "PricebookEntry",
                "referenceId": "PricebookEntryRef7"
            },
            "IsActive": true,
            "UnitPrice": 100,
            "UseStandardPrice": false,
            "Product2Id":"@Product2Ref2",
            "ProductSellingModelId": "@ProductSellingModelRef1",
            "Pricebook2Id": "SM_PRICEBOOK_ID",
            "CurrencyISOCode": "USD"
        },
        {
            "attributes": {
                "type": "PricebookEntry",
                "referenceId": "PricebookEntryRef8"
            },
            "IsActive": true,
            "UnitPrice": 500,
            "UseStandardPrice": false,
            "Product2Id":"@Product2Ref3",
            "ProductSellingModelId": "@ProductSellingModelRef3",
            "Pricebook2Id": "SM_PRICEBOOK_ID",
            "CurrencyISOCode": "USD"
        },
        {
            "attributes": {
                "type": "PricebookEntry",
                "referenceId": "PricebookEntryRef9"
            },
            "IsActive": true,
            "UnitPrice": 25,
            "UseStandardPrice": false,
            "Product2Id":"@Product2Ref4",
            "ProductSellingModelId": "@ProductSellingModelRef1",
            "Pricebook2Id": "SM_PRICEBOOK_ID",
            "CurrencyISOCode": "USD"
        },
        {
            "attributes": {
                "type": "PricebookEntry",
                "referenceId": "PricebookEntryRef10"
            },
            "IsActive": true,
            "UnitPrice": 35,
            "UseStandardPrice": false,
            "Product2Id":"@Product2Ref4",
            "ProductSellingModelId": "@ProductSellingModelRef3",
            "Pricebook2Id": "SM_PRICEBOOK_ID",
            "CurrencyISOCode": "USD"
        },
        {
            "attributes": {
                "type": "PricebookEntry",
                "referenceId": "PricebookEntryRef11"
            },
            "IsActive": true,
            "UnitPrice": 1000,
            "UseStandardPrice": false,
            "Product2Id":"@Product2Ref1",
            "ProductSellingModelId": "@ProductSellingModelRef2",
            "Pricebook2Id": "COMMERCE_PRICEBOOK_ID",
            "CurrencyISOCode": "USD"
        },
        {
            "attributes": {
                "type": "PricebookEntry",
                "referenceId": "PricebookEntryRef12"
            },
            "IsActive": true,
            "UnitPrice": 100,
            "UseStandardPrice": false,
            "Product2Id":"@Product2Ref2",
            "ProductSellingModelId": "@ProductSellingModelRef1",
            "Pricebook2Id": "COMMERCE_PRICEBOOK_ID",
            "CurrencyISOCode": "USD"
        },
        {
            "attributes": {
                "type": "PricebookEntry",
                "referenceId": "PricebookEntryRef13"
            },
            "IsActive": true,
            "UnitPrice": 500,
            "UseStandardPrice": false,
            "Product2Id":"@Product2Ref3",
            "ProductSellingModelId": "@ProductSellingModelRef3",
            "Pricebook2Id": "COMMERCE_PRICEBOOK_ID",
            "CurrencyISOCode": "USD"
        },
        {
            "attributes": {
                "type": "PricebookEntry",
                "referenceId": "PricebookEntryRef14"
            },
            "IsActive": true,
            "UnitPrice": 25,
            "UseStandardPrice": false,
            "Product2Id":"@Product2Ref4",
            "ProductSellingModelId": "@ProductSellingModelRef1",
            "Pricebook2Id": "COMMERCE_PRICEBOOK_ID",
            "CurrencyISOCode": "USD"
        },
        {
            "attributes": {
                "type": "PricebookEntry",
                "referenceId": "PricebookEntryRef15"
            },
            "IsActive": true,
            "UnitPrice": 35,
            "UseStandardPrice": false,
            "Product2Id":"@Product2Ref4",
            "ProductSellingModelId": "@ProductSellingModelRef3",
            "Pricebook2Id": "COMMERCE_PRICEBOOK_ID",
            "CurrencyISOCode": "USD"
        },
        {
            "attributes": {
                "type": "PricebookEntry",
                "referenceId": "PricebookEntryRef16"
            },
            "IsActive": true,
            "UnitPrice": 1200,
            "UseStandardPrice": false,
            "Product2Id":"@Product2Ref5",
            "ProductSellingModelId": "@ProductSellingModelRef4",
            "Pricebook2Id": "STANDARD_PRICEBOOK_ID",
            "CurrencyISOCode": "USD"
        },
        {
            "attributes": {
                "type": "PricebookEntry",
                "referenceId": "PricebookEntryRef17"
            },
            "IsActive": true,
            "UnitPrice": 1200,
            "UseStandardPrice": false,
            "Product2Id":"@Product2Ref5",
            "ProductSellingModelId": "@ProductSellingModelRef4",
            "Pricebook2Id": "SM_PRICEBOOK_ID",
            "CurrencyISOCode": "USD"
        },
        {
            "attributes": {
                "type": "PricebookEntry",
                "referenceId": "PricebookEntryRef18"
            },
            "IsActive": true,
            "UnitPrice": 1200,
            "UseStandardPrice": false,
            "Product2Id":"@Product2Ref5",
            "ProductSellingModelId": "@ProductSellingModelRef4",
            "Pricebook2Id": "COMMERCE_PRICEBOOK_ID",
            "CurrencyISOCode": "USD"
        },
        {
            "attributes": {
                "type": "PricebookEntry",
                "referenceId": "PricebookEntryRef19"
            },
            "IsActive": true,
            "UnitPrice": 915,
            "UseStandardPrice": false,
            "Product2Id":"@Product2Ref1",
            "ProductSellingModelId": "@ProductSellingModelRef2",
            "Pricebook2Id": "STANDARD_PRICEBOOK_ID",
            "CurrencyISOCode": "EUR"
        },
        {
            "attributes": {
                "type": "PricebookEntry",
                "referenceId": "PricebookEntryRef20"
            },
            "IsActive": true,
            "UnitPrice": 785,
            "UseStandardPrice": false,
            "Product2Id":"@Product2Ref1",
            "ProductSellingModelId": "@ProductSellingModelRef2",
            "Pricebook2Id": "STANDARD_PRICEBOOK_ID",
            "CurrencyISOCode": "GBP"
        },
        {
            "attributes": {
                "type": "PricebookEntry",
                "referenceId": "PricebookEntryRef21"
            },
            "IsActive": true,
            "UnitPrice": 1500,
            "UseStandardPrice": false,
            "Product2Id":"@Product2Ref1",
            "ProductSellingModelId": "@ProductSellingModelRef2",
            "Pricebook2Id": "STANDARD_PRICEBOOK_ID",
            "CurrencyISOCode": "AUD"
        },
        {
            "attributes": {
                "type": "PricebookEntry",
                "referenceId": "PricebookEntryRef22"
            },
            "IsActive": true,
            "UnitPrice": 1325,
            "UseStandardPrice": false,
            "Product2Id":"@Product2Ref1",
            "ProductSellingModelId": "@ProductSellingModelRef2",
            "Pricebook2Id": "STANDARD_PRICEBOOK_ID",
            "CurrencyISOCode": "CAD"
        },
        {
            "attributes": {
                "type": "PricebookEntry",
                "referenceId": "PricebookEntryRef23"
            },
            "IsActive": true,
            "UnitPrice": 1350,
            "UseStandardPrice": false,
            "Product2Id":"@Product2Ref1",
            "ProductSellingModelId": "@ProductSellingModelRef2",
            "Pricebook2Id": "STANDARD_PRICEBOOK_ID",
            "CurrencyISOCode": "SGD"
        },
        {
            "attributes": {
                "type": "PricebookEntry",
                "referenceId": "PricebookEntryRef24"
            },
            "IsActive": true,
            "UnitPrice": 915,
            "UseStandardPrice": false,
            "Product2Id":"@Product2Ref1",
            "ProductSellingModelId": "@ProductSellingModelRef2",
            "Pricebook2Id": "SM_PRICEBOOK_ID",
            "CurrencyISOCode": "EUR"
        },
        {
            "attributes": {
                "type": "PricebookEntry",
                "referenceId": "PricebookEntryRef25"
            },
            "IsActive": true,
            "UnitPrice": 785,
            "UseStandardPrice": false,
            "Product2Id":"@Product2Ref1",
            "ProductSellingModelId": "@ProductSellingModelRef2",
            "Pricebook2Id": "SM_PRICEBOOK_ID",
            "CurrencyISOCode": "GBP"
        },
        {
            "attributes": {
                "type": "PricebookEntry",
                "referenceId": "PricebookEntryRef26"
            },
            "IsActive": true,
            "UnitPrice": 1500,
            "UseStandardPrice": false,
            "Product2Id":"@Product2Ref1",
            "ProductSellingModelId": "@ProductSellingModelRef2",
            "Pricebook2Id": "SM_PRICEBOOK_ID",
            "CurrencyISOCode": "AUD"
        },
        {
            "attributes": {
                "type": "PricebookEntry",
                "referenceId": "PricebookEntryRef27"
            },
            "IsActive": true,
            "UnitPrice": 1325,
            "UseStandardPrice": false,
            "Product2Id":"@Product2Ref1",
            "ProductSellingModelId": "@ProductSellingModelRef2",
            "Pricebook2Id": "SM_PRICEBOOK_ID",
            "CurrencyISOCode": "CAD"
        },
        {
            "attributes": {
                "type": "PricebookEntry",
                "referenceId": "PricebookEntryRef28"
            },
            "IsActive": true,
            "UnitPrice": 1350,
            "UseStandardPrice": false,
            "Product2Id":"@Product2Ref1",
            "ProductSellingModelId": "@ProductSellingModelRef2",
            "Pricebook2Id": "SM_PRICEBOOK_ID",
            "CurrencyISOCode": "SGD"
        },
        {
            "attributes": {
                "type": "PricebookEntry",
                "referenceId": "PricebookEntryRef29"
            },
            "IsActive": true,
            "UnitPrice": 915,
            "UseStandardPrice": false,
            "Product2Id":"@Product2Ref1",
            "ProductSellingModelId": "@ProductSellingModelRef2",
            "Pricebook2Id": "COMMERCE_PRICEBOOK_ID",
            "CurrencyISOCode": "EUR"
        },
        {
            "attributes": {
                "type": "PricebookEntry",
                "referenceId": "PricebookEntryRef30"
            },
            "IsActive": true,
            "UnitPrice": 785,
            "UseStandardPrice": false,
            "Product2Id":"@Product2Ref1",
            "ProductSellingModelId": "@ProductSellingModelRef2",
            "Pricebook2Id": "COMMERCE_PRICEBOOK_ID",
            "CurrencyISOCode": "GBP"
        },
        {
            "attributes": {
                "type": "PricebookEntry",
                "referenceId": "PricebookEntryRef31"
            },
            "IsActive": true,
            "UnitPrice": 1500,
            "UseStandardPrice": false,
            "Product2Id":"@Product2Ref1",
            "ProductSellingModelId": "@ProductSellingModelRef2",
            "Pricebook2Id": "COMMERCE_PRICEBOOK_ID",
            "CurrencyISOCode": "AUD"
        },
        {
            "attributes": {
                "type": "PricebookEntry",
                "referenceId": "PricebookEntryRef32"
            },
            "IsActive": true,
            "UnitPrice": 1325,
            "UseStandardPrice": false,
            "Product2Id":"@Product2Ref1",
            "ProductSellingModelId": "@ProductSellingModelRef2",
            "Pricebook2Id": "COMMERCE_PRICEBOOK_ID",
            "CurrencyISOCode": "CAD"
        },
        {
            "attributes": {
                "type": "PricebookEntry",
                "referenceId": "PricebookEntryRef33"
            },
            "IsActive": true,
            "UnitPrice": 1350,
            "UseStandardPrice": false,
            "Product2Id":"@Product2Ref1",
            "ProductSellingModelId": "@ProductSellingModelRef2",
            "Pricebook2Id": "COMMERCE_PRICEBOOK_ID",
            "CurrencyISOCode": "SGD"
        }
    ]
}